motile_toolbox/__init__.py
motile_toolbox/candidate_graph/__init__.py
motile_toolbox/candidate_graph/compute_graph.py
motile_toolbox/candidate_graph/conflict_sets.py
motile_toolbox/candidate_graph/graph_attributes.py
motile_toolbox/candidate_graph/graph_to_nx.py
motile_toolbox/candidate_graph/iou.py
motile_toolbox/candidate_graph/utils.py
motile_toolbox/utils/__init__.py
motile_toolbox/utils/loading_utils.py
motile_toolbox/utils/relabel_segmentation.py
motile_toolbox/visualization/__init__.py
motile_toolbox/visualization/napari_utils.py
motile_toolbox/visualization/plot_motile_graphs.py
motile_toolbox-0.4.0.dist-info/METADATA
motile_toolbox-0.4.0.dist-info/WHEEL
motile_toolbox-0.4.0.dist-info/top_level.txt
motile_toolbox-0.4.0.dist-info/RECORD
