Metadata-Version: 2.1
Name: motile_toolbox
Version: 0.4.0
Summary: A toolbox for tracking with (motile)[https://github.com/funkelab/motile].
Author-email: Funke Lab <malinmayorc@janelia.hhmi.org>
License: BSD 3-Clause License
Project-URL: homepage, https://github.com/funkelab/motile_toolbox
Project-URL: repository, https://github.com/funkelab/motile_toolbox
Classifier: Programming Language :: Python :: 3
Requires-Python: >=3.10
Requires-Dist: motile
Requires-Dist: networkx
Requires-Dist: numpy
Requires-Dist: matplotlib
Requires-Dist: scikit-image
Requires-Dist: tqdm
Requires-Dist: zarr
Requires-Dist: plotly
Provides-Extra: dev
Requires-Dist: pytest; extra == "dev"
Requires-Dist: pytest-cov; extra == "dev"
Requires-Dist: mypy; extra == "dev"
Requires-Dist: pdoc; extra == "dev"
Requires-Dist: pre-commit; extra == "dev"
Requires-Dist: types-tqdm; extra == "dev"
Requires-Dist: pytest-unordered; extra == "dev"
Requires-Dist: ruff; extra == "dev"
